LTEpy/__init__.py
LTEpy/atom.py
LTEpy/constants.py
LTEpy/lte.py
LTEpy/plot.py
tests/__init__.py
tests/test_atom.py
tests/test_boltzmann_factor.py
tests/test_planck.py
LTEpy-1.0.4.dist-info/LICENSE
LTEpy-1.0.4.dist-info/METADATA
LTEpy-1.0.4.dist-info/WHEEL
LTEpy-1.0.4.dist-info/top_level.txt
LTEpy-1.0.4.dist-info/RECORD
